<Database>
    <GameDBStringTable ID="LOC_PL_PATCH_1_1_23">
    
        <LanguageCode>pl</LanguageCode>
        <LanguageNameLocalized>Polski</LanguageNameLocalized>
        
        <Contributors>
            <Name>Oxymoron Games</Name>
        </Contributors>

        <!-- Note: feel free to rearrange any sentences with the parameter {1} so the word order makes sense -->
        <LocalizedStrings>
            <!-- RELATED FILE: StringTable[Language]Options.xml -->
            <GameDBLocalizedString>      <LocID>OPTIONS_NO_EMPLOYEE_LIMIT</LocID>                <Text>Wyłącz limit pracowników (wymaga szybkiego komputera)</Text>  </GameDBLocalizedString>
                                                                                                 
            <!-- Old, wasn't translated in most languages -->                                    
            <GameDBLocalizedString>      <LocID>OPTIONS_RUN_IN_BACKGORUND</LocID>                <Text>Praca w tle</Text>  </GameDBLocalizedString>

            <!--New loading tips -->
            <GameDBLocalizedString>      <LocID>LOADING_TIP_SELECTING_OBJ</LocID>                <Text>Wybieraj obiekty za pomocą klawisza Shift.</Text>  </GameDBLocalizedString>
            <GameDBLocalizedString>      <LocID>LOADING_TIP_TAKING_OVER_PATIENTS</LocID>         <Text>Możesz automatycznie przejmować kontrolę nad wszystkimi pacjentami na każdym oddziale.</Text>  </GameDBLocalizedString>
            <GameDBLocalizedString>      <LocID>LOADING_TIP_SURGERY_PRIORITY</LocID>             <Text>Pacjent zbyt długo czeka na operację? Przesuń go na początek listy!</Text>  </GameDBLocalizedString>

            
            <!-- RELATED FILE: StringTable[Language]UI.xml -->                                   
            <GameDBLocalizedString>       <LocID>CLOUD_SAVE</LocID>                              <Text>Zapis w chmurze</Text>  </GameDBLocalizedString>
            <GameDBLocalizedString>       <LocID>TOOLTIP_BUILDING_EQUIPMENT_CLONE</LocID>        <Text>Wybierz obiekt do skopiowania</Text>  </GameDBLocalizedString>
            <GameDBLocalizedString>       <LocID>TOOLTIP_BUILDING_DOORS_CLONE</LocID>            <Text>Wybierz drzwi do skopiowania</Text>  </GameDBLocalizedString>
            <GameDBLocalizedString>       <LocID>TOOLTIP_BUILDING_WALLS_CLONE</LocID>            <Text>Wybierz ścianę do skopiowania</Text>  </GameDBLocalizedString>

            <GameDBLocalizedString>       <LocID>TABLE_SURGERY_HEADING</LocID>                   <Text>Zaplanowane operacje: {1}</Text>  </GameDBLocalizedString>
            <GameDBLocalizedString>       <LocID>TABLE_SURGERY_SURGERY</LocID>                   <Text>Operacja</Text>  </GameDBLocalizedString>
            <GameDBLocalizedString>       <LocID>TABLE_SURGERY_PRIORITY</LocID>                  <Text>Priorytet</Text>  </GameDBLocalizedString>
            <GameDBLocalizedString>       <LocID>TABLE_SURGERY_CANCEL_PRIORITY</LocID>           <Text>Anuluj priorytet</Text>  </GameDBLocalizedString>
            <GameDBLocalizedString>       <LocID>TABLE_SURGERY_ORDER</LocID>                     <Text>Kolejność</Text>  </GameDBLocalizedString>
            <GameDBLocalizedString>       <LocID>TOOLTIP_SURGERY_PRIORITY</LocID>                <Text>Ustaw najwyższy priorytet dla tej operacji (przesuń na początek)</Text>  </GameDBLocalizedString>
            <GameDBLocalizedString>       <LocID>TOOLTIP_SURGERY_CANCEL_PRIORITY</LocID>         <Text>Anuluj wysoki priorytet tej operacji</Text>  </GameDBLocalizedString>
            <GameDBLocalizedString>       <LocID>TOOLTIP_TABLE_SURGERIES</LocID>                 <Text>Zarządzaj zaplanowanymi operacjami na aktywnym oddziale</Text>  </GameDBLocalizedString>
            
            <GameDBLocalizedString>       <LocID>TOOLTIP_BUILDING_EQUIPMENT_CLONE</LocID>        <Text>Wybierz obiekt do skopiowania (domyślny skrót: i)</Text>  </GameDBLocalizedString>
            <GameDBLocalizedString>       <LocID>TOOLTIP_BUILDING_DOORS_CLONE</LocID>            <Text>Wybierz drzwi do skopiowania (domyślny skrót: i)</Text>  </GameDBLocalizedString>
            <GameDBLocalizedString>       <LocID>TOOLTIP_BUILDING_WALLS_CLONE</LocID>            <Text>Wybierz ścianę do skopiowania (domyślny skrót: i)</Text>  </GameDBLocalizedString>
            <GameDBLocalizedString>       <LocID>TOOLTIP_BUILDING_FLOORS_CLONE</LocID>           <Text>Wybierz piętra do skopiowania (domyślny skrót: i)</Text>  </GameDBLocalizedString>
            
            
            <!-- RELATED FILE: StringTable[Language]BuildingMode.xml -->                         
            <GameDBLocalizedString>      <LocID>PREFAB_OBJECT_AMBULANCE_PARKING</LocID>                <Text>Parking dla karetek</Text>  </GameDBLocalizedString>
            <GameDBLocalizedString>      <LocID>PREFAB_OBJECT_AMBULANCE_PARKING_DESCRIPTION</LocID>    <Text>Parking dla karetek. Automatycznie zastąpi obecny.</Text>  </GameDBLocalizedString>

            <GameDBLocalizedString>      <LocID>PREFAB_OBJECT_AMBULANCE_PARKING_STRIPES</LocID>        <Text>Parking dla karetek</Text>  </GameDBLocalizedString>

            <GameDBLocalizedString>      <LocID>PREFAB_OBJECT_AMBULANCE_UNLOADING</LocID>              <Text>Podjazd dla karetek</Text>  </GameDBLocalizedString>
            <GameDBLocalizedString>      <LocID>PREFAB_OBJECT_AMBULANCE_UNLOADING_DESCRIPTION</LocID>  <Text>Podjazd dla karetek, z których wyprowadzani są pacjenci. Automatycznie zastąpi obecny.</Text>  </GameDBLocalizedString>
            
            <GameDBLocalizedString>      <LocID>NOT_ALLOWED_AMBULANCES_OWNED</LocID>             <Text>nie można edytować w szpitalu z aktywnymi karetkami.</Text>  </GameDBLocalizedString>
            <GameDBLocalizedString>      <LocID>NOT_ALLOWED_AMBULANCE_UNLOADING</LocID>          <Text>nie można edytować, kiedy karetka wiezie/zabiera pacjenta.</Text>  </GameDBLocalizedString>
            
            
            <!-- RELATED FILE: StringTable[Language]Characters.xml -->
            <GameDBLocalizedString>      <LocID>PATIENT_IS_BEING_CALLED</LocID>                  <Text>Następny pacjent</Text>  </GameDBLocalizedString>
                                                                                                 
            <GameDBLocalizedString>      <LocID>SAT_MOD_EXPOSED_TO_OUTDOORS</LocID>              <Text>narażenie na warunki atmosferyczne</Text>  </GameDBLocalizedString>
            
            <GameDBLocalizedString>      <LocID>ANESTHESIOLOGIST_DESCRIPTION_V2</LocID>          <Text>Lekarz w dyżurce, specjalizacja: {1}.\n\nDostępność:\nNa tym oddziale: {2}\nW OIT: {3}</Text>  </GameDBLocalizedString>
                                                                                                 
            <GameDBLocalizedString>      <LocID>GoingToStatLab</LocID>                           <Text>W drodze do laboratorium</Text>  </GameDBLocalizedString>

            <!--USG and ECG to Radiology department-->
            <GameDBLocalizedString>      <LocID>ROOM_TYPE_RADIO_CARDIO_UNIT</LocID>                             <Text>Gabinet kardiografii</Text>	</GameDBLocalizedString>
            <GameDBLocalizedString>      <LocID>ROOM_TYPE_RADIO_SONO_UNIT</LocID>                               <Text>Gabinet sonografii</Text>	</GameDBLocalizedString>
            <!-- PREFABS -->
            <GameDBLocalizedString>      <LocID>PREFAB_ROOM_CARDIOVASCULAR_UNIT_RAD_ABBR</LocID>                    <Text>Gabinet kardiografii - 6 x 6</Text>	</GameDBLocalizedString>
            <GameDBLocalizedString>      <LocID>PREFAB_ROOM_SONOGRAPHY_UNIT_RAD_ABBR</LocID>                        <Text>Gabinet sonografii - 6 x 6</Text>	</GameDBLocalizedString>

        </LocalizedStrings>
        
    </GameDBStringTable>
</Database>
