<Database>    <GameDBStringTable ID="LOC_TR_DLC_DOCTOR_MODE">            <LanguageCode>tr</LanguageCode>        <LanguageNameLocalized>Türkçe</LanguageNameLocalized>                <Contributors>            <Name>Oxymoron Games</Name>        </Contributors>        <!-- Note: feel free to rearrange any sentences with the parameter {1} so the word order makes sense -->        <LocalizedStrings>            <GameDBLocalizedString>      <LocID>DLC_DOCTOR_MODE</LocID>                                     <Text>Doktor Modu DLC'si</Text>  </GameDBLocalizedString>                        <!-- RELATED FILE: StringTable[Language]Notifications.xml -->            <GameDBLocalizedString>      <LocID>NOTIF_CONTROLLED_PATIENT_COLLAPSING</LocID>                 <Text>Kontrol edilen doktorun hastası bayıldı ve taşındı.</Text>  </GameDBLocalizedString>            <GameDBLocalizedString>      <LocID>NOTIF_CONTROLLED_PATIENT_COLLAPSING_TEXT</LocID>            <Text>Kontrol edilen bir doktorun hastası bayıldı ve {1} birimine taşındı. Hasta başka bir doktora atandı.</Text>  </GameDBLocalizedString>            <!-- RELATED FILE: StringTable[Language]UI.xml -->            <GameDBLocalizedString>      <LocID>TOOLTIP_DOCTOR_MODE_BUTTON</LocID>                          <Text>Doktor modu (F8)</Text>  </GameDBLocalizedString>                                                                                                                      <GameDBLocalizedString>      <LocID>CONTROLLED_BY_PLAYERS_DOCTOR</LocID>                        <Text>Oyuncunun doktoruna atandı</Text>  </GameDBLocalizedString>                                                                                                                      <GameDBLocalizedString>      <LocID>SEGMENT_HEADING_CONTROLLED_DOCTORS</LocID>                  <Text>Kontrol edilen doktorlar</Text>  </GameDBLocalizedString>            <GameDBLocalizedString>      <LocID>SEGMENT_HEADING_DOCTORS_PATIENTS</LocID>                    <Text>Doktorun hastaları</Text>  </GameDBLocalizedString>            <GameDBLocalizedString>      <LocID>SEGMENT_HEADING_CONTROLLED_PATIENTS</LocID>                 <Text>Kontrol edilen hastalar</Text>  </GameDBLocalizedString>            <GameDBLocalizedString>      <LocID>SEGMENT_HEADING_YOUR_PATIENTS</LocID>                       <Text>Senin hastaların</Text>  </GameDBLocalizedString>            <GameDBLocalizedString>      <LocID>SEGMENT_HEADING_HIGHLIGHTS</LocID>                          <Text>Önemli anlar</Text>  </GameDBLocalizedString>                                                                                                                      <GameDBLocalizedString>      <LocID>CHAR_FILTER_HAZARD</LocID>                                  <Text>Tehlike</Text>  </GameDBLocalizedString>            <GameDBLocalizedString>      <LocID>CHAR_FILTER_PROFIT</LocID>                                  <Text>Kâr</Text>  </GameDBLocalizedString>            <GameDBLocalizedString>      <LocID>CHAR_FILTER_SATISFACTION</LocID>                            <Text>Memnuniyet</Text>  </GameDBLocalizedString>            <GameDBLocalizedString>      <LocID>CHAR_FILTER_CRITICAL</LocID>                                <Text>Kritik</Text>  </GameDBLocalizedString>            <GameDBLocalizedString>      <LocID>CHAR_FILTER_WAITING_FOR_TRT</LocID>                         <Text>Tedavi bekleniyor</Text>  </GameDBLocalizedString>            <GameDBLocalizedString>      <LocID>CHAR_FILTER_WAITING_FOR_EXM</LocID>                         <Text>Muayene bekleniyor</Text>  </GameDBLocalizedString>            <GameDBLocalizedString>      <LocID>CHAR_FILTER_NO_DIAGNOSIS</LocID>                            <Text>Teşhis yok</Text>  </GameDBLocalizedString>            <GameDBLocalizedString>      <LocID>CHAR_FILTER_CONTROLLED</LocID>                              <Text>Kontrol ediliyor</Text>  </GameDBLocalizedString>                                                                                                                      <GameDBLocalizedString>      <LocID>HARD_CORE_MODE_DIAGNOSE_PERCENTAGE</LocID>                  <Text>Teşhis sırasında ipucu bulunamadı</Text>  </GameDBLocalizedString>            <GameDBLocalizedString>      <LocID>HARD_CORE_MODE_HIDDEN_SYMPTOMS_NUMBER</LocID>               <Text>Gizli semptomların sayısını gizle</Text>  </GameDBLocalizedString>            <GameDBLocalizedString>      <LocID>HARD_CORE_MODE_PULSING_HIDDEN_SYMPTOMS</LocID>              <Text>Gizli semptomların yanıp sönmesi özelliğini kapat</Text>  </GameDBLocalizedString>                                                                                                                      <GameDBLocalizedString>      <LocID>BEGINNER_MODE</LocID>                                       <Text>Normal mod</Text>  </GameDBLocalizedString>            <GameDBLocalizedString>      <LocID>EASY_MODE</LocID>                                           <Text>Stajyer modu</Text>  </GameDBLocalizedString>            <GameDBLocalizedString>      <LocID>MEDIUM_MODE</LocID>                                         <Text>Asistan modu</Text>  </GameDBLocalizedString>            <GameDBLocalizedString>      <LocID>HARDCORE_MODE</LocID>                                       <Text>Uzman modu</Text>  </GameDBLocalizedString>                                                                                                                      <GameDBLocalizedString>      <LocID>TOOLTIP_CODE_BLUE</LocID>                                   <Text>Mavi Kod: Bu hastayı kritik durumdaki hastalarla aynı öncelikte tedavi et</Text>  </GameDBLocalizedString>            <GameDBLocalizedString>      <LocID>TOOLTIP_ADD_CONTROLLED_DOCTOR</LocID>                       <Text>Kontrol edeceğin doktoru ve hastalarını seç</Text>  </GameDBLocalizedString>                                                                                                                      <GameDBLocalizedString>      <LocID>SHOW_PORTRAITS_OR_DIAGNOSES</LocID>                         <Text>Hastanın portresini veya teşhislerini göster</Text>  </GameDBLocalizedString>                                                                                                                      <GameDBLocalizedString>      <LocID>TOOLTIP_COLOR_GUIDE</LocID>                                 <Text>Renk rehberi</Text>  </GameDBLocalizedString>            <GameDBLocalizedString>      <LocID>TOOLTIP_COLOR_GUIDE_PLAYER</LocID>                          <Text>Oyuncu bekleniyor</Text>  </GameDBLocalizedString>                                                                                                                      <GameDBLocalizedString>      <LocID>FOLLOW_CONTROLLED_DOCTOR</LocID>                            <Text>Ekran açısını seçili doktor merkezde olacak şekilde kilitle</Text>  </GameDBLocalizedString>            <GameDBLocalizedString>      <LocID>REMOVE_DOCTOR_FROM_CONTROLLED</LocID>                       <Text>Doktoru kontrol edilen doktorlar listesinden çıkar</Text>  </GameDBLocalizedString>                                                                                                                      <!-- DLC Tutorial and campaign level menu -->                                                             <GameDBLocalizedString>      <LocID>DOC_MODE_LEVEL_TUTORIAL_01</LocID>                          <Text>Doktor Modu: Eğitim</Text>  </GameDBLocalizedString>            <GameDBLocalizedString>      <LocID>DOC_MODE_LEVEL_TUTORIAL_01_DESCRIPTION</LocID>              <Text>Doktorları kontrol etmenin temellerini öğren.</Text>  </GameDBLocalizedString>            <GameDBLocalizedString>      <LocID>DOC_MODE_LEVEL_CAMPAIGN_01</LocID>                          <Text>Doktor Modu: Emekli oldun, çok şükür!</Text>  </GameDBLocalizedString>            <GameDBLocalizedString>      <LocID>DOC_MODE_LEVEL_CAMPAIGN_01_DESCRIPTION</LocID>              <Text>Tam anlamıyla emekli olmadan önce uzmanlığına ihtiyacımız olan son bir iş var. Eğitebileceğin ve deneyimlerini aktarabileceğin en iyi çalışanları bulabilir misin?</Text>  </GameDBLocalizedString>            <!-- DLC Tutorial texts -->            <GameDBLocalizedString>      <LocID>DLC_TUTORIAL_01_WELCOME</LocID>                             <Text>Selam patron, sistemimizdeki yeni moda bir göz atalım. Bu modun adı Doktor Modu; bu mod sayesinde doktorlarımızın kontrolünü elimize alıp hastalarımızla daha yakından ilgilenebileceğiz.</Text>  </GameDBLocalizedString>            <GameDBLocalizedString>      <LocID>DLC_TUTORIAL_TEXT_DOC_MODE</LocID>                          <Text><![CDATA[Ekranın sol üst köşesindeki <b><i>butona tıklayabilir</i></b> veya <b><i>F8 tuşuna basabilirsin</i></b>. \n\nBir doktoru kontrol etmeye başladığında ve senin ilgilenmeni gerektiren bir durum olduğunda bu buton yanıp sönmeye başlar.]]></Text>  </GameDBLocalizedString>            <GameDBLocalizedString>      <LocID>DLC_TUTORIAL_DOC_MODE_OVERALL_INFO</LocID>                  <Text>Doktor Modu ekranın sağında bulunur. Hadi temel özelliklerinin üzerinden birlikte geçelim.</Text>  </GameDBLocalizedString>            <GameDBLocalizedString>      <LocID>DLC_TUTORIAL_DOC_MODE_HARDCORE_MODE</LocID>                 <Text><![CDATA[İlk bakacağımız şey zorluk ayarı olacak. Ayarlar panelini açmak için <b><i>butona tıkla</i></b>.]]></Text>  </GameDBLocalizedString>            <GameDBLocalizedString>      <LocID>DLC_TUTORIAL_DOC_MODE_HARDCORE_MODE_OPENED</LocID>          <Text>Buradan hastanın kartında görünen farklı ipuçlarını gizleyerek teşhis sürecinin hangi kısmını kendin için zorlaştıracağını seçebilirsin.</Text>  </GameDBLocalizedString>            <GameDBLocalizedString>      <LocID>DLC_TUTORIAL_DOC_MODE_CONTROLLED_DOCTORS</LocID>            <Text><![CDATA[İlk büyük bölüm kontrol ettiğin doktorları gösterir. <b><i>+ simgesine tıklayıp</i></b> etkin departmandaki bir doktoru seçerek o doktoru kontrol etmeye başlayabilirsin. <b><i>Şimdi bunu yapmayı bir dene bakalım.</i></b>]]></Text>  </GameDBLocalizedString>            <GameDBLocalizedString>      <LocID>DLC_TUTORIAL_DOC_MODE_CONTROLLED_DOCTOR_PATIENTS</LocID>    <Text>Bir doktoru kontrol etmeye başladığında onun ilgilendiği bütün hastalardan sen sorumlu olursun; hastalar aşağıdaki listede görünür. \n\nBir hastayı iyileştirdiğine hasta kartı üzerinden elinle taburcu etmeyi unutma. </Text>  </GameDBLocalizedString>            <GameDBLocalizedString>      <LocID>DLC_TUTORIAL_DOC_MODE_CONTROLLED_PATIENTS</LocID>           <Text>Bir sonraki bölme ise, yönetim modundaki "Bütün Hastaları Al" butonunu veya hasta kartlarını kullanarak üzerine aldığın hastaları gösterir.\n\nHasta portresinin arka plan rengi hastanın o anki durumunu belirtir. Soru işaretinin üzerine gelerek bu renklerin anlamlarını öğrenebilirsin.</Text>  </GameDBLocalizedString>            <GameDBLocalizedString>      <LocID>DLC_TUTORIAL_DOC_MODE_HIGHLIGHTS</LocID>                    <Text>En son bölme de hastalarının ve personelinin belirli bazı bilgilerini işaretleyerek göz önünde tutmanı sağlar; böylece mutlu veya mutsuz olduklarını, ne için beklediklerini veya tehlike altında olup olmadıklarını bir bakışta görebilirsin.</Text>  </GameDBLocalizedString>            <GameDBLocalizedString>      <LocID>DLC_TUTORIAL_01_TASK</LocID>                                <Text>Doktor Modu'yla ilgili önemli olan her şeyin üzerinden geçtik. Şimdi bir deneme yapalım; sigorta şirketi için gereken hedefi tamamla.</Text>  </GameDBLocalizedString>            <GameDBLocalizedString>      <LocID>DLC_TUTORIAL_01_FINISHED</LocID>                            <Text>İşi kapmaya başladın gibi görünüyor. Bir sonraki hastanende başarılar!</Text>  </GameDBLocalizedString>                        <!-- DLC campaign level texts -->            <GameDBLocalizedString>      <LocID>DLC_CAMPAIGN_01_WELCOME_INFO</LocID>                        <Text>Selam patron, emekli olmak istediğini biliyorum ama yeteneklerine bir kez daha ihtiyacımız var. Bu gördüğün yer en iyi eğitim hastanelerinden biri olacaktı ve farklı alanlara yönelen uzmanları eğitecekti. Fakat maalesef bu hastane hiç açılamadı.</Text>  </GameDBLocalizedString>            <GameDBLocalizedString>      <LocID>DLC_CAMPAIGN_01_WELCOME_MORE_INFO</LocID>                   <Text>Bina tamamlandı ama bu hastaneyi işletebilecek kadar becerikli birini bulamadık; ayrıca, bazı birimleri ve pahalı ekipmanı da eksik kaldı. Bu hastaneyi açıp çalışır hale getirebilir misin? İşe yeni personel al, birimleri yeniden aç ve senin yerini alabilecek uzman birini eğit; bunları hallettikten sonra seni rahat bırakacağız.</Text>  </GameDBLocalizedString>            <GameDBLocalizedString>      <LocID>DLC_CAMPAIGN_01_CREATE_DOCTOR</LocID>                       <Text>İşi kabul ettiğine göre senin yerini alabilecek kişiyi oluşturmaya başlayabilirsin.</Text>  </GameDBLocalizedString>            <GameDBLocalizedString>      <LocID>DLC_CAMPAIGN_01_TAKE_OVER_DOCTOR</LocID>                    <Text>Harika, benim içime sindi. Klinik çalışmaya başladığına göre kontrolün altındaki doktoru alıp teşhis sürecinin bütün inceliklerini öğretmeye başlayabilirsin.</Text>  </GameDBLocalizedString>            <GameDBLocalizedString>      <LocID>DLC_CAMPAIGN_01_NEW_INSURANCE</LocID>                       <Text>İşler tıkırında. Böyle gidersen doktorun hemen uzman olacak; aynen devam et! Bu sırada kardeş şirketimiz olan sigorta firması da bize daha fazla teklif sunmaya başlayacak.</Text>  </GameDBLocalizedString>            <GameDBLocalizedString>      <LocID>DLC_CAMPAIGN_01_LAST_INSURANCE</LocID>                      <Text>Tanıdığımız başka bir sigorta firması için de başarmamız gereken bazı hedefler var; onlara da odaklanalım. Ana amacımız hepsini tamamlayarak hastanenin kendi ayakları üzerinde durabileceğinden emin olmak.</Text>  </GameDBLocalizedString>            <GameDBLocalizedString>      <LocID>DLC_CAMPAIGN_01_FINISHED</LocID>                            <Text>Eline sağlık! Muhteşem bir hastane kurdun ve yerine gelecek kişiyi eğittin. Bıraktığın mirasın ülkenin her yerinden insana yardımcı olacağını bilerek gönül rahatlığıyla emekli olabilirsin.</Text>  </GameDBLocalizedString>                        <!-- DLC  Achievements-->            <GameDBLocalizedString>      <LocID>DLC_ACHIEVEMENT_TUTORIAL_01</LocID>                         <Text>Destek tekerlerine elveda!</Text>  </GameDBLocalizedString>            <GameDBLocalizedString>      <LocID>DLC_ACHIEVEMENT_TUTORIAL_01_DESCRIPTION</LocID>             <Text>İndirilebilir içerikle gelen Doktor Modu eğitimi tamamla.</Text>  </GameDBLocalizedString>                        <GameDBLocalizedString>      <LocID>DLC_ACHIEVEMENT_LEVEL_1</LocID>                             <Text>Doktor Mouse'u çağırın!</Text>  </GameDBLocalizedString>            <GameDBLocalizedString>      <LocID>DLC_ACHIEVEMENT_LEVEL_1_DESCRIPTION</LocID>                 <Text>İndirilebilir içerikle gelen Doktor Modu bölümünü tamamla.</Text>  </GameDBLocalizedString>                        <GameDBLocalizedString>      <LocID>DLC_ACHIEVEMENT_CREATE_ONE_CHAR</LocID>                     <Text>Seni seçtim...</Text>  </GameDBLocalizedString>            <GameDBLocalizedString>      <LocID>DLC_ACHIEVEMENT_CREATE_ONE_CHAR_DESCRIPTION</LocID>         <Text>Kendi karakterini oluştur.</Text>  </GameDBLocalizedString>                        <GameDBLocalizedString>      <LocID>DLC_ACHIEVEMENT_CREATE_MORE_CHAR</LocID>                    <Text>...ve seni, seni ve seni de.</Text>  </GameDBLocalizedString>            <GameDBLocalizedString>      <LocID>DLC_ACHIEVEMENT_CREATE_MORE_CHAR_DESCRIPTION</LocID>        <Text>10 karakter oluştur.</Text>  </GameDBLocalizedString>                        <GameDBLocalizedString>      <LocID>DLC_ACHIEVEMENT_SPECIALIST_MODE</LocID>                     <Text>Marifetlerini Görelim</Text>  </GameDBLocalizedString>            <GameDBLocalizedString>      <LocID>DLC_ACHIEVEMENT_SPECIALIST_MODE_DESCRIPTION</LocID>         <Text>Uzman modunu etkinleştir.</Text>  </GameDBLocalizedString>                        <GameDBLocalizedString>      <LocID>DLC_ACHIEVEMENT_SPECIALIST_MODE_PATIENT</LocID>             <Text>Hiçbir Şey Görmedin</Text>  </GameDBLocalizedString>            <GameDBLocalizedString>      <LocID>DLC_ACHIEVEMENT_SPECIALIST_MODE_PATIENT_DESCRIPTION</LocID> <Text>Uzman modunda ilk hastanı tedavi et.</Text>  </GameDBLocalizedString>                        <GameDBLocalizedString>      <LocID>DLC_ACHIEVEMENT_SPECIALIST_MODE_PATIENTS</LocID>            <Text>Seni Uzman İlan Ediyorum!</Text>  </GameDBLocalizedString>            <GameDBLocalizedString>      <LocID>DLC_ACHIEVEMENT_SPECIALIST_MODE_PATIENTS_DESCRIPTION</LocID><Text>Uzman modunda 20 hasta tedavi et.</Text>  </GameDBLocalizedString>                        <GameDBLocalizedString>      <LocID>DLC_ACHIEVEMENT_CAMERA_ROTATION</LocID>                     <Text>Dönsün Dünya</Text>  </GameDBLocalizedString>            <GameDBLocalizedString>      <LocID>DLC_ACHIEVEMENT_CAMERA_ROTATION_DESCRIPTION</LocID>         <Text>Kamerayı 100 kere döndür.</Text>  </GameDBLocalizedString>            <!-- Character editor -->            <GameDBLocalizedString>      <LocID>CHAR_EDITOR_NAME</LocID>                                    <Text>Karakter Oluşturucu</Text>  </GameDBLocalizedString>            <GameDBLocalizedString>      <LocID>CHAR_EDITOR_INFO</LocID>                                    <Text>Seç, düzenle, oluştur...</Text>  </GameDBLocalizedString>            <GameDBLocalizedString>      <LocID>CHAR_EDITOR_SELECT_GENDER_AGE</LocID>                       <Text>Cinsiyeti seç ve yaşı belirle:</Text>  </GameDBLocalizedString>            <GameDBLocalizedString>      <LocID>CHAR_EDITOR_GENDER</LocID>                                  <Text>Cinsiyet</Text>  </GameDBLocalizedString>            <GameDBLocalizedString>      <LocID>CHAR_EDITOR_AGE</LocID>                                     <Text>Yaş</Text>  </GameDBLocalizedString>            <GameDBLocalizedString>      <LocID>CHAR_EDITOR_RANDOM</LocID>                                  <Text>Rastgele</Text>  </GameDBLocalizedString>            <GameDBLocalizedString>      <LocID>CHAR_EDITOR_APPEARANCE</LocID>                              <Text>Görünümü belirle:</Text>  </GameDBLocalizedString>            <GameDBLocalizedString>      <LocID>CHAR_EDITOR_SKIN</LocID>                                    <Text>Ten</Text>  </GameDBLocalizedString>            <GameDBLocalizedString>      <LocID>CHAR_EDITOR_HAIR</LocID>                                    <Text>Saç</Text>  </GameDBLocalizedString>            <GameDBLocalizedString>      <LocID>CHAR_EDITOR_EYES</LocID>                                    <Text>Göz</Text>  </GameDBLocalizedString>            <GameDBLocalizedString>      <LocID>CHAR_EDITOR_LIPS</LocID>                                    <Text>Dudak</Text>  </GameDBLocalizedString>            <GameDBLocalizedString>      <LocID>CHAR_EDITOR_BEARD</LocID>                                   <Text>Sakal</Text>  </GameDBLocalizedString>            <GameDBLocalizedString>      <LocID>CHAR_EDITOR_NOSE</LocID>                                    <Text>Burun</Text>  </GameDBLocalizedString>            <GameDBLocalizedString>      <LocID>CHAR_EDITOR_WRINKLES</LocID>                                <Text>Kırışıklıklar</Text>  </GameDBLocalizedString>            <GameDBLocalizedString>      <LocID>CHAR_EDITOR_ACCESSORIES</LocID>                             <Text>Aksesuarlar</Text>  </GameDBLocalizedString>            <GameDBLocalizedString>      <LocID>CHAR_EDITOR_PERSONAL_INFO</LocID>                           <Text>Kişisel bilgiler:</Text>  </GameDBLocalizedString>            <GameDBLocalizedString>      <LocID>CHAR_EDITOR_OCCUPATION</LocID>                              <Text>Meslek:</Text>  </GameDBLocalizedString>            <GameDBLocalizedString>      <LocID>CHAR_EDITOR_LEVEL</LocID>                                   <Text>Seviye:</Text>  </GameDBLocalizedString>            <GameDBLocalizedString>      <LocID>CHAR_EDITOR_SKIN_TONES</LocID>                              <Text>Ten renkleri</Text>  </GameDBLocalizedString>            <GameDBLocalizedString>      <LocID>CHAR_EDITOR_HAIR_TONES</LocID>                              <Text>Saç ve sakal renkleri</Text>  </GameDBLocalizedString>            <GameDBLocalizedString>      <LocID>CHAR_EDITOR_PERKS</LocID>                                   <Text>Artılarını seç:</Text>  </GameDBLocalizedString>            <GameDBLocalizedString>      <LocID>CHAR_EDITOR_PERKS_NUMBER</LocID>                            <Text>{1} tane seç:</Text>  </GameDBLocalizedString>            <GameDBLocalizedString>      <LocID>CHAR_EDITOR_RANDOM</LocID>                                  <Text>Rastgele</Text>  </GameDBLocalizedString>            <GameDBLocalizedString>      <LocID>CHAR_EDITOR_RESET</LocID>                                   <Text>Sıfırla</Text>  </GameDBLocalizedString>            <GameDBLocalizedString>      <LocID>CHAR_EDITOR_CREATE</LocID>                                  <Text>{1} $ karşılığında oluştur.</Text>  </GameDBLocalizedString>            <!-- Insurance objectives -->            <GameDBLocalizedString>      <LocID>CREATED_DOCTORS</LocID>                                     <Text>(İşe alım kartındaki) Karakter Oluşturucu ile {1} doktor oluştur</Text>  </GameDBLocalizedString>            <!-- Parameter {1} is a number, parameter {2} is a name of a department -->            <GameDBLocalizedString>      <LocID>CREATED_DOCTORS_AT_DEPARTMENT</LocID>                       <Text>(İşe alım kartındaki) Karakter Oluşturucu ile {2} biriminde {1} doktor oluştur</Text>  </GameDBLocalizedString>            <GameDBLocalizedString>      <LocID>TREATED_PATIENTS_WITH_INTERN_MODE_AT_DEPARTMENT</LocID>     <Text>Stajyer modunda oynarken {2} biriminde kontrol ettiğin doktorla {1} hasta tedavi et</Text>  </GameDBLocalizedString>            <GameDBLocalizedString>      <LocID>TREATED_PATIENTS_WITH_RESIDENT_MODE_AT_DEPARTMENT</LocID>   <Text>Asistan modunda oynarken {2} biriminde kontrol ettiğin doktorla {1} hasta tedavi et</Text>  </GameDBLocalizedString>            <GameDBLocalizedString>      <LocID>TREATED_PATIENTS_WITH_SPECIALIST_MODE_AT_DEPARTMENT</LocID> <Text>Uzman modunda oynarken {2} biriminde kontrol ettiğin doktorla {1} hasta tedavi et</Text>  </GameDBLocalizedString>            <GameDBLocalizedString>      <LocID>TREATED_CONTROLLED_PATIENTS_AT_DEPARTMENT</LocID>           <Text>{2} biriminde kontrol ettiğin doktorla {1} hasta tedavi et</Text>  </GameDBLocalizedString>            <!-- Parameter {1} is name of the level (like Resident or Attending), parameter {2} is name of the profession, currently only Doctor -->            <GameDBLocalizedString>      <LocID>REACHED_CERTAIN_LEVEL_WITH_CREATED_CHARACTER</LocID>        <Text>Oluşturduğun {1} ile {2}. seviyeye yüksel</Text>  </GameDBLocalizedString>            <!-- Parameter {1} is a number, parameter {2} is a name of a department -->            <GameDBLocalizedString>      <LocID>NO_DEAD_CONTROLLED_PATIENTS_DAYS</LocID>                    <Text>{1} gün boyunca kontrol ettiğin doktorun {2} biriminde hiçbir hastası ölmesin</Text>  </GameDBLocalizedString>                        <GameDBLocalizedString>      <LocID>REACHED_DOCTORS_RATING</LocID>                              <Text>Kontrol ettiğin doktorun puanı {1} olsun</Text>  </GameDBLocalizedString>                        <!-- Parameter {1} is difficulty level, see BEGINNER_MODE, EASY_MODE above in this file  -->            <GameDBLocalizedString>      <LocID>CORRECTLY_DIAGNOSED_CONTROLLED_DOCTORS_PATIENTS</LocID>     <Text>{1} biriminde kontrol ettiğin doktorla hastalara doğru teşhis koy</Text>  </GameDBLocalizedString>            <GameDBLocalizedString>      <LocID>TREATED_CONTROLLED_DOCTORS_PATIENTS</LocID>                 <Text>{1} ile oynarken kontrol ettiğin doktorların hastalarını tedavi et</Text>  </GameDBLocalizedString>            <!-- Parameter {1} is a number -->            <GameDBLocalizedString>      <LocID>EXPERIENCE_POINTS_FOR_CREATED_CHARACTERS</LocID>            <Text>Oyuncuların oluşturduğu tüm karakterlere {1} tecrübe puanı</Text>  </GameDBLocalizedString>            <GameDBLocalizedString>      <LocID>EXPERIENCE_POINTS_FOR_CONTROLLED_DOCTORS</LocID>            <Text>Oyuncuların kontrol ettiği tüm karakterlere {1} tecrübe puanı</Text>  </GameDBLocalizedString>                        <!-- RELATED FILE: StringTable[Language]Names.xml -->            <GameDBLocalizedString>    <LocID>IN_COM_CAMPAIGN_CAMPAIGN_1B</LocID>                           <Text>ÜfleGeçer Sigorta</Text>  </GameDBLocalizedString>            <GameDBLocalizedString>    <LocID>IN_COM_DC_MD_NAME</LocID>                           			<Text>Hay Aksi Ltd. Şti.</Text>  </GameDBLocalizedString>        </LocalizedStrings>    </GameDBStringTable></Database>    